sciencedates/__init__.py
sciencedates/ticks.py
sciencedates-1.4.1.data/scripts/date2doy.py
sciencedates-1.4.1.data/scripts/randomdate.py
sciencedates-1.4.1.dist-info/DESCRIPTION.rst
sciencedates-1.4.1.dist-info/METADATA
sciencedates-1.4.1.dist-info/RECORD
sciencedates-1.4.1.dist-info/WHEEL
sciencedates-1.4.1.dist-info/metadata.json
sciencedates-1.4.1.dist-info/top_level.txt
