Metadata-Version: 2.0
Name: sciencedates
Version: 1.4.1
Summary: Date conversions used in the sciences.
Home-page: https://github.com/scivision/sciencedates
Author: Michael Hirsch, Ph.D.
Author-email: UNKNOWN
License: UNKNOWN
Platform: UNKNOWN
Classifier: Development Status :: 5 - Production/Stable
Classifier: Environment :: Console
Classifier: Intended Audience :: Science/Research
Classifier: License :: OSI Approved :: MIT License
Classifier: Operating System :: OS Independent
Classifier: Programming Language :: Python :: 3.6
Classifier: Programming Language :: Python :: 3.7
Classifier: Topic :: Scientific/Engineering :: GIS
Requires-Python: >=3.6
Requires-Dist: numpy
Requires-Dist: pytz
Requires-Dist: python-dateutil
Provides-Extra: plot
Requires-Dist: xarray; extra == 'plot'
Requires-Dist: matplotlib; extra == 'plot'
Provides-Extra: tests
Requires-Dist: pytest; extra == 'tests'
Requires-Dist: nose; extra == 'tests'
Requires-Dist: coveralls; extra == 'tests'
Requires-Dist: flake8; extra == 'tests'
Requires-Dist: mypy; extra == 'tests'
